{"stats":{"minecraft:mined":{"minecraft:cyan_wool":46},"minecraft:custom":{"minecraft:time_since_rest":3614,"minecraft:play_one_minute":31055,"minecraft:crouch_one_cm":9828,"minecraft:sprint_one_cm":180642,"minecraft:deaths":4,"minecraft:damage_taken":1721,"minecraft:walk_one_cm":39299,"minecraft:sneak_time":3237,"minecraft:walk_under_water_one_cm":902,"minecraft:drop":22,"minecraft:jump":1013,"minecraft:damage_dealt":142,"minecraft:leave_game":3,"minecraft:time_since_death":3612,"minecraft:walk_on_water_one_cm":342,"minecraft:damage_dealt_absorbed":32,"minecraft:swim_one_cm":5260,"minecraft:player_kills":2,"minecraft:fall_one_cm":32031,"minecraft:fly_one_cm":270253},"minecraft:killed_by":{"minecraft:player":3},"minecraft:picked_up":{"minecraft:diamond":4,"minecraft:iron_ingot":271,"minecraft:cyan_wool":82,"minecraft:gold_ingot":64,"minecraft:emerald":65},"minecraft:used":{"minecraft:wooden_sword":32,"minecraft:tnt":2,"minecraft:cyan_wool":170,"minecraft:obsidian":48},"minecraft:dropped":{"minecraft:iron_ingot":8,"minecraft:diamond":2,"minecraft:emerald":12}},"DataVersion":2586}